davify/__init__.py
davify/cli.py
davify/config.py
davify/housekeeping.py
davify/keyring.py
davify/transform.py
davify/upload.py
davify-1.2.0.dist-info/LICENSE
davify-1.2.0.dist-info/METADATA
davify-1.2.0.dist-info/WHEEL
davify-1.2.0.dist-info/entry_points.txt
davify-1.2.0.dist-info/RECORD
