Metadata-Version: 2.1
Name: davify
Version: 1.2.0
Summary: Davify uploads files to webdav servers and provides a download link for accessing them.
Home-page: https://github.com/AlbertWeichselbraun/davify
License: GPL3
Keywords: webdav
Author: Albert Weichselbraun
Author-email: albert@weichselbraun.net
Requires-Python: >=3.8,<4.0
Classifier: License :: Other/Proprietary License
Classifier: Programming Language :: Python :: 3
Classifier: Programming Language :: Python :: 3.8
Classifier: Programming Language :: Python :: 3.9
Classifier: Programming Language :: Python :: 3.10
Classifier: Programming Language :: Python :: 3.11
Classifier: Programming Language :: Python :: 3.12
Requires-Dist: pyperclip (>=1.8.2,<2.0.0)
Requires-Dist: qrcode (>=7.4.2,<8.0.0)
Requires-Dist: requests (>=2.32.2,<3.0.0)
Requires-Dist: secretstorage (>=3.3.3,<4.0.0)
